INSTALL.txt
README.txt
bootstrap.py
buildout.cfg
setup.py
src/bebop/__init__.py
src/bebop.protocol.egg-info/PKG-INFO
src/bebop.protocol.egg-info/SOURCES.txt
src/bebop.protocol.egg-info/dependency_links.txt
src/bebop.protocol.egg-info/not-zip-safe
src/bebop.protocol.egg-info/requires.txt
src/bebop.protocol.egg-info/top_level.txt
src/bebop/protocol/README.txt
src/bebop/protocol/__init__.py
src/bebop/protocol/bebop.protocol-configure.zcml
src/bebop/protocol/browser.py
src/bebop/protocol/browser.txt
src/bebop/protocol/configure.zcml
src/bebop/protocol/directive.py
src/bebop/protocol/generic.txt
src/bebop/protocol/interfaces.py
src/bebop/protocol/meta.zcml
src/bebop/protocol/protocol.py
src/bebop/protocol/tests.py
src/bebop/protocol/demo/__init__.py
src/bebop/protocol/demo/extension.py
src/bebop/protocol/demo/test.pt
src/bebop/protocol/demo/hello/__init__.py
src/bebop/protocol/demo/hello/allinone.py
src/bebop/protocol/demo/hello/configure.zcml
src/bebop/protocol/demo/hello/greeting.py
src/bebop/protocol/demo/hello/interfaces.py
src/bebop/protocol/demo/hello/world.py
src/bebop/protocol/demo/package/__init__.py
src/bebop/protocol/demo/package/adapter.py
src/bebop/protocol/demo/package/interfaces.py
src/bebop/protocol/demo/package/protocol.zcml
src/bebop/protocol/demo/package/security.py
src/bebop/protocol/demo/package/subscriber.py
src/bebop/protocol/demo/package/utility.py
