Metadata-Version: 1.0
Name: bebop.protocol
Version: 0.1
Summary: This package allows to register components from Python. It also provides a basic implementation of generic functions in Zope3
Home-page: http://svn.kmrc.de/projects/devel/bebop.protocol
Author: Bebop Team
Author-email: uwe_oestermeier@iwm-kmrc.de
License: GPL
Keywords: zope3 ZCML generation configuration
Platform: any
Classifier: Development Status :: 3 - Alpha
Classifier: Environment :: Web Environment
Classifier: Intended Audience :: Developers
Classifier: License :: OSI Approved :: GNU General Public License (GPL)
Classifier: Programming Language :: Python
Classifier: Natural Language :: English
Classifier: Operating System :: OS Independent
Classifier: Topic :: Internet :: WWW/HTTP
Classifier: Framework :: Zope3
